Dockme/__init__.py
Dockme/chng_dc.py
Dockme/delet_container.py
Dockme/delet_image.py
Dockme/funkt_classes.py
Dockme/get_image.py
Dockme/run_command_in_con.py
Dockme/run_container.py
Dockme/run_portainer.py
Dockme/simple_funtion.py
Dockme/start_stop_compose.py
Dockme/stop_container.py
Dockme-0.2.4.dist-info/METADATA
Dockme-0.2.4.dist-info/WHEEL
Dockme-0.2.4.dist-info/top_level.txt
Dockme-0.2.4.dist-info/RECORD
