Metadata-Version: 2.1
Name: Dockme
Version: 0.2.4
Summary: Dockme in version 0.2.4
Home-page: 
Author: Jonn Morgenstern
Author-email: Jean-Luc Morgenstern <mintjonn1410@gmail.com>
Project-URL: Homepage, https://github.com/LetsJonnTV/Dockmy
Project-URL: Bug Tracker, https://github.com/LetsJonnTV/Dockmy
Classifier: Programming Language :: Python :: 3
Classifier: License :: OSI Approved :: MIT License
Classifier: Operating System :: OS Independent
Requires-Python: >=3.7
